message_match/__init__.py
message_match/message_match.py
message_match-1.0.0.dist-info/DESCRIPTION.rst
message_match-1.0.0.dist-info/METADATA
message_match-1.0.0.dist-info/RECORD
message_match-1.0.0.dist-info/WHEEL
message_match-1.0.0.dist-info/metadata.json
message_match-1.0.0.dist-info/top_level.txt
