Metadata-Version: 2.0
Name: message-match
Version: 1.0.0
Summary: Fast, simple message matching
Provides-Extra: dev
Requires-Dist: check-manifest; extra == 'dev'
Provides-Extra: test
Requires-Dist: pytest; extra == 'test'
Requires-Dist: sys; extra == 'test'
